MANIFEST.in
README.rst
setup.cfg
setup.py
Gistpy.egg-info/PKG-INFO
Gistpy.egg-info/SOURCES.txt
Gistpy.egg-info/dependency_links.txt
Gistpy.egg-info/entry_points.txt
Gistpy.egg-info/requires.txt
Gistpy.egg-info/top_level.txt
Gistpy.egg-info/zip-safe
gistpy/__init__.py
gistpy/argaction.py
gistpy/argbuilder.py
gistpy/auth.py
gistpy/clipboard.py
gistpy/constant.py
gistpy/dispatch.py
gistpy/errors.py
gistpy/query.py
gistpy/util.py
gistpy/command/__init__.py
gistpy/command/create.py
gistpy/command/delete.py
gistpy/command/edit.py
gistpy/command/get.py
gistpy/command/register.py
gistpy/command/simple.py