Metadata-Version: 1.1
Name: Gistpy
Version: 0.2.1
Summary: Command line client for gist.
Home-page: https://github.com/bluele/Gistpy
Author: Jun Kimura
Author-email: jksmphone@gmail.com
License: MIT
Keywords: cli client gist github sourcecode
Platform: UNKNOWN
Classifier: Development Status :: 3 - Alpha
Classifier: Environment :: Console
Classifier: Topic :: System :: Shells
Classifier: License :: OSI Approved :: MIT License
Classifier: Programming Language :: Python
Classifier: Programming Language :: Python :: 2
Classifier: Programming Language :: Python :: 2.6
Classifier: Programming Language :: Python :: 2.7
